{
  "2024_1Q": {
    "금융상품손익": 1942,
    "지분법손익": 803,
    "감가상각비": 20565,
    "당기순이익": 96322,
    "영업이익": 130211,
    "기부금": 94,
    "외환손익": 10009,
    "이자손익": 4735,
    "매출원가": 349090,
    "기타판관비": 19183,
    "판매비와관리비": 202273,
    "광고선전비": 24097,
    "매출총이익": 332484,
    "매출액": 1014057,
    "인건비": 19658,
    "수수료": 118770,
    "선물환손익": 473,
    "기타손익": 2913,
    "법인세비용": 31837,
    "영업외손익": 21031,
    "법인세비용차감전순이익": 128159,
    "배당수익": 62
  },
  "2024_1Q_Year": {
    "금융상품손익": 1942,
    "지분법손익": 803,
    "감가상각비": 20565,
    "당기순이익": 96322,
    "영업이익": 130211,
    "기부금": 94,
    "외환손익": 10009,
    "이자손익": 4735,
    "매출원가": 349090,
    "기타판관비": 19183,
    "판매비와관리비": 202273,
    "광고선전비": 24097,
    "매출총이익": 332484,
    "매출액": 1014057,
    "인건비": 19658,
    "수수료": 118770,
    "선물환손익": 473,
    "기타손익": 2913,
    "법인세비용": 31837,
    "영업외손익": 21031,
    "법인세비용차감전순이익": 128159,
    "배당수익": 62
  },
  "2024_2Q": {
    "금융상품손익": 747,
    "지분법손익": 800,
    "감가상각비": 21538,
    "당기순이익": 73951,
    "영업이익": 91801,
    "기부금": 409,
    "외환손익": 5537,
    "이자손익": 4846,
    "매출원가": 240349,
    "기타판관비": 16666,
    "판매비와관리비": 179497,
    "광고선전비": 16955,
    "매출총이익": 271299,
    "매출액": 782946,
    "인건비": 22001,
    "수수료": 102336,
    "선물환손익": 471,
    "기타손익": 1412,
    "법인세비용": 24005,
    "영업외손익": 16367,
    "법인세비용차감전순이익": 97956,
    "배당수익": 2144
  },
  "2024_2Q_Year": {
    "금융상품손익": 2689,
    "지분법손익": 1603,
    "감가상각비": 42103,
    "당기순이익": 170273,
    "영업이익": 222012,
    "기부금": 503,
    "외환손익": 15546,
    "이자손익": 9581,
    "매출원가": 589438,
    "기타판관비": 35849,
    "판매비와관리비": 381770,
    "광고선전비": 41052,
    "매출총이익": 603782,
    "매출액": 1797003,
    "인건비": 41660,
    "수수료": 221107,
    "선물환손익": 944,
    "기타손익": 4325,
    "법인세비용": 55842,
    "영업외손익": 37398,
    "법인세비용차감전순이익": 226115,
    "배당수익": 2207
  },
  "2024_3Q": {
    "금융상품손익": 2467,
    "지분법손익": 9098,
    "감가상각비": 23267,
    "당기순이익": 79801,
    "영업이익": 108305,
    "기부금": 1910,
    "외환손익": 5066,
    "이자손익": 4486,
    "매출원가": 332084,
    "기타판관비": 17057,
    "판매비와관리비": 176616,
    "광고선전비": 19902,
    "매출총이익": 284921,
    "매출액": 901927,
    "인건비": 19926,
    "수수료": 96464,
    "선물환손익": 1022,
    "기타손익": 7353,
    "법인세비용": 30039,
    "영업외손익": 32490,
    "법인세비용차감전순이익": 109840,
    "배당수익": 1088
  },
  "2024_3Q_Year": {
    "금융상품손익": 5156,
    "지분법손익": 10701,
    "감가상각비": 65370,
    "당기순이익": 250074,
    "영업이익": 330317,
    "기부금": 2413,
    "외환손익": 20612,
    "이자손익": 14068,
    "매출원가": 921523,
    "기타판관비": 52907,
    "판매비와관리비": 558387,
    "광고선전비": 60954,
    "매출총이익": 888704,
    "매출액": 2698930,
    "인건비": 61586,
    "수수료": 317570,
    "선물환손익": 1966,
    "기타손익": 11678,
    "법인세비용": 85881,
    "영업외손익": 69888,
    "법인세비용차감전순이익": 335955,
    "배당수익": 3295
  },
  "2024_4Q": {
    "금융상품손익": 845,
    "지분법손익": 17757,
    "감가상각비": 23439,
    "당기순이익": 105886,
    "영업이익": 120420,
    "기부금": 826,
    "외환손익": 16231,
    "이자손익": 4538,
    "매출원가": 376511,
    "기타판관비": 23655,
    "판매비와관리비": 237868,
    "광고선전비": 32179,
    "매출총이익": 358289,
    "매출액": 1093089,
    "인건비": 22684,
    "수수료": 135912,
    "선물환손익": 685,
    "기타손익": 14784,
    "법인세비용": 35461,
    "영업외손익": 55396,
    "법인세비용차감전순이익": 141346,
    "배당수익": -271
  },
  "2024_Year": {
    "금융상품손익": 6002,
    "지분법손익": 28458,
    "감가상각비": 88809,
    "당기순이익": 355960,
    "영업이익": 450737,
    "기부금": 3239,
    "외환손익": 36843,
    "이자손익": 18605,
    "매출원가": 1298034,
    "기타판관비": 76561,
    "판매비와관리비": 796255,
    "광고선전비": 93133,
    "매출총이익": 1246993,
    "매출액": 3792019,
    "인건비": 84270,
    "수수료": 453482,
    "선물환손익": 2651,
    "기타손익": 26462,
    "법인세비용": 121341,
    "영업외손익": 125284,
    "법인세비용차감전순이익": 477301,
    "배당수익": 3024
  },
  "2025_1Q": {
    "금융상품손익": 1129,
    "지분법손익": 766,
    "감가상각비": 24508,
    "당기순이익": 82569,
    "영업이익": 123616,
    "기부금": 5,
    "외환손익": 21907,
    "이자손익": 4360,
    "매출원가": 555544,
    "기타판관비": 20573,
    "판매비와관리비": 206117,
    "광고선전비": 24609,
    "매출총이익": 329733,
    "매출액": 1011232,
    "인건비": 21639,
    "수수료": 114788,
    "선물환손익": 3457,
    "기타손익": 6021,
    "법인세비용": 28094,
    "영업외손익": 37982,
    "법인세비용차감전순이익": 110663,
    "배당수익": 337
  },
  "2025_1Q_Year": {
    "금융상품손익": 1129,
    "지분법손익": 766,
    "감가상각비": 24508,
    "당기순이익": 82569,
    "영업이익": 123616,
    "기부금": 5,
    "외환손익": 21907,
    "이자손익": 4360,
    "매출원가": 555544,
    "기타판관비": 20573,
    "판매비와관리비": 206117,
    "광고선전비": 24609,
    "매출총이익": 329733,
    "매출액": 1011232,
    "인건비": 21639,
    "수수료": 114788,
    "선물환손익": 3457,
    "기타손익": 6021,
    "법인세비용": 28094,
    "영업외손익": 37982,
    "법인세비용차감전순이익": 110663,
    "배당수익": 337
  },
  "2025_2Q": {
    "금융상품손익": -46,
    "지분법손익": 828,
    "감가상각비": 22115,
    "당기순이익": 62639,
    "영업이익": 84030,
    "기부금": 0,
    "외환손익": 10246,
    "이자손익": 3017,
    "매출원가": 375150,
    "기타판관비": 17184,
    "판매비와관리비": 174877,
    "광고선전비": 19539,
    "매출총이익": 258906,
    "매출액": 757742,
    "인건비": 20876,
    "수수료": 95162,
    "선물환손익": 5637,
    "기타손익": 6117,
    "법인세비용": 23444,
    "영업외손익": 25836,
    "법인세비용차감전순이익": 86083,
    "배당수익": 37
  },
  "2025_2Q_Year": {
    "금융상품손익": 1084,
    "지분법손익": 1594,
    "감가상각비": 46623,
    "당기순이익": 145208,
    "영업이익": 207646,
    "기부금": 5,
    "외환손익": 32153,
    "이자손익": 7377,
    "매출원가": 930694,
    "기타판관비": 37757,
    "판매비와관리비": 380993,
    "광고선전비": 44148,
    "매출총이익": 588640,
    "매출액": 1768974,
    "인건비": 42514,
    "수수료": 209950,
    "선물환손익": 9094,
    "기타손익": 12138,
    "법인세비용": 51538,
    "영업외손익": 63819,
    "법인세비용차감전순이익": 196746,
    "배당수익": 373
  },
  "2025_3Q": {
    "금융상품손익": 668,
    "지분법손익": 9116,
    "감가상각비": 22262,
    "당기순이익": 100695,
    "영업이익": 128020,
    "기부금": 78,
    "외환손익": 9435,
    "이자손익": 3480,
    "매출원가": 539112,
    "기타판관비": 19468,
    "판매비와관리비": 180935,
    "광고선전비": 25032,
    "매출총이익": 308955,
    "매출액": 948514,
    "인건비": 20266,
    "수수료": 93907,
    "선물환손익": -5393,
    "기타손익": 5715,
    "법인세비용": 34583,
    "영업외손익": 23580,
    "법인세비용차감전순이익": 135278,
    "배당수익": 482
  },
  "2025_3Q_Year": {
    "금융상품손익": 1752,
    "지분법손익": 10710,
    "감가상각비": 68885,
    "당기순이익": 245903,
    "영업이익": 335666,
    "기부금": 83,
    "외환손익": 41588,
    "이자손익": 10856,
    "매출원가": 1469806,
    "기타판관비": 57225,
    "판매비와관리비": 561928,
    "광고선전비": 69180,
    "매출총이익": 897594,
    "매출액": 2717488,
    "인건비": 62780,
    "수수료": 303857,
    "선물환손익": 3701,
    "기타손익": 17853,
    "법인세비용": 86121,
    "영업외손익": 87399,
    "법인세비용차감전순이익": 332024,
    "배당수익": 855
  },
  "2025_4Q": {
    "금융상품손익": 0,
    "지분법손익": 0,
    "감가상각비": 0,
    "당기순이익": 0,
    "영업이익": 0,
    "기부금": 0,
    "외환손익": 0,
    "이자손익": 0,
    "매출원가": 0,
    "기타판관비": 0,
    "판매비와관리비": 0,
    "광고선전비": 0,
    "매출총이익": 0,
    "매출액": 0,
    "인건비": 0,
    "수수료": 0,
    "선물환손익": 0,
    "기타손익": 0,
    "법인세비용": 0,
    "영업외손익": 0,
    "법인세비용차감전순이익": 0,
    "배당수익": 0
  },
  "2025_Year": {
    "금융상품손익": 1752,
    "지분법손익": 10710,
    "감가상각비": 68885,
    "당기순이익": 245903,
    "영업이익": 335666,
    "기부금": 83,
    "외환손익": 41588,
    "이자손익": 10856,
    "매출원가": 1469806,
    "기타판관비": 57225,
    "판매비와관리비": 561928,
    "광고선전비": 69180,
    "매출총이익": 897594,
    "매출액": 2717488,
    "인건비": 62780,
    "수수료": 303857,
    "선물환손익": 3701,
    "기타손익": 17853,
    "법인세비용": 86121,
    "영업외손익": 87399,
    "법인세비용차감전순이익": 332024,
    "배당수익": 855
  }
}